signal8/__init__.py
signal8/main.py
signal8/signal8.py
signal8/utils/__init__.py
signal8/utils/core.py
signal8/utils/problems.py
signal8/utils/scenario.py
signal8/utils/simple_env.py
Signal8-5.1.1.dist-info/LICENSE
Signal8-5.1.1.dist-info/METADATA
Signal8-5.1.1.dist-info/WHEEL
Signal8-5.1.1.dist-info/top_level.txt
Signal8-5.1.1.dist-info/RECORD
