Metadata-Version: 2.1
Name: Signal8
Version: 5.1.1
Summary: A multi-agent environment inspired by the Lewis Signaling Game, featuring eight unique problem configurations with both static and dynamic obstacles.
Home-page: https://github.com/ethanmclark1/signal8
Author: Ethan Clark
Author-email: eclark715@gmail.com.com
Classifier: License :: OSI Approved :: MIT License
Classifier: Programming Language :: Python
License-File: LICENSE
